<?xml version="1.0" encoding="UTF-8"?>
<!DOCTYPE mapper PUBLIC "-//mybatis.org//DTD Mapper 3.0//EN" "http://mybatis.org/dtd/mybatis-3-mapper.dtd">
<mapper namespace="ljl.dao.TStudentMapper">
  <resultMap id="BaseResultMap" type="ljl.entity.TStudent">
    <!--
      WARNING - @mbg.generated
      This element is automatically generated by MyBatis Generator, do not modify.
    -->
    <id column="STUID" jdbcType="DECIMAL" property="stuid" />
    <result column="NAME" jdbcType="VARCHAR" property="name" />
    <result column="AGE" jdbcType="DECIMAL" property="age" />
    <result column="SEX" jdbcType="CHAR" property="sex" />
  </resultMap>
  <sql id="Base_Column_List">
    <!--
      WARNING - @mbg.generated
      This element is automatically generated by MyBatis Generator, do not modify.
    -->
    STUID, NAME, AGE, SEX
  </sql>
  <select id="selectByPrimaryKey" parameterType="java.lang.Long" resultMap="BaseResultMap">
    <!--
      WARNING - @mbg.generated
      This element is automatically generated by MyBatis Generator, do not modify.
    -->
    select 
    <include refid="Base_Column_List" />
    from T_STUDENT
    where STUID = #{stuid,jdbcType=DECIMAL}
  </select>
  <delete id="deleteByPrimaryKey" parameterType="java.lang.Long">
    <!--
      WARNING - @mbg.generated
      This element is automatically generated by MyBatis Generator, do not modify.
    -->
    delete from T_STUDENT
    where STUID = #{stuid,jdbcType=DECIMAL}
  </delete>
  <insert id="insert" parameterType="ljl.entity.TStudent">
    <!--
      WARNING - @mbg.generated
      This element is automatically generated by MyBatis Generator, do not modify.
    -->
    insert into T_STUDENT (STUID, NAME, AGE, 
      SEX)
    values (#{stuid,jdbcType=DECIMAL}, #{name,jdbcType=VARCHAR}, #{age,jdbcType=DECIMAL}, 
      #{sex,jdbcType=CHAR})
  </insert>
  <insert id="insertSelective" parameterType="ljl.entity.TStudent">
    <!--
      WARNING - @mbg.generated
      This element is automatically generated by MyBatis Generator, do not modify.
    -->
    insert into T_STUDENT
    <trim prefix="(" suffix=")" suffixOverrides=",">
      <if test="stuid != null">
        STUID,
      </if>
      <if test="name != null">
        NAME,
      </if>
      <if test="age != null">
        AGE,
      </if>
      <if test="sex != null">
        SEX,
      </if>
    </trim>
    <trim prefix="values (" suffix=")" suffixOverrides=",">
      <if test="stuid != null">
        #{stuid,jdbcType=DECIMAL},
      </if>
      <if test="name != null">
        #{name,jdbcType=VARCHAR},
      </if>
      <if test="age != null">
        #{age,jdbcType=DECIMAL},
      </if>
      <if test="sex != null">
        #{sex,jdbcType=CHAR},
      </if>
    </trim>
  </insert>
  <update id="updateByPrimaryKeySelective" parameterType="ljl.entity.TStudent">
    <!--
      WARNING - @mbg.generated
      This element is automatically generated by MyBatis Generator, do not modify.
    -->
    update T_STUDENT
    <set>
      <if test="name != null">
        NAME = #{name,jdbcType=VARCHAR},
      </if>
      <if test="age != null">
        AGE = #{age,jdbcType=DECIMAL},
      </if>
      <if test="sex != null">
        SEX = #{sex,jdbcType=CHAR},
      </if>
    </set>
    where STUID = #{stuid,jdbcType=DECIMAL}
  </update>
  <update id="updateByPrimaryKey" parameterType="ljl.entity.TStudent">
    <!--
      WARNING - @mbg.generated
      This element is automatically generated by MyBatis Generator, do not modify.
    -->
    update T_STUDENT
    set NAME = #{name,jdbcType=VARCHAR},
      AGE = #{age,jdbcType=DECIMAL},
      SEX = #{sex,jdbcType=CHAR}
    where STUID = #{stuid,jdbcType=DECIMAL}
  </update>
</mapper>